ConfinedBrownianAnalysis/__init__.py
ConfinedBrownianAnalysis/Analyse/Dedrift.py
ConfinedBrownianAnalysis/Analyse/Observables.py
ConfinedBrownianAnalysis/Analyse/__init__.py
ConfinedBrownianAnalysis/Diffusion/SFI_bases.py
ConfinedBrownianAnalysis/Diffusion/SFI_data.py
ConfinedBrownianAnalysis/Diffusion/SFI_demo_Lorenz.py
ConfinedBrownianAnalysis/Diffusion/SFI_demo_particles.py
ConfinedBrownianAnalysis/Diffusion/SFI_inference.py
ConfinedBrownianAnalysis/Diffusion/SFI_langevin.py
ConfinedBrownianAnalysis/Diffusion/SFI_plotting_toolkit.py
ConfinedBrownianAnalysis/Diffusion/SFI_projectors.py
ConfinedBrownianAnalysis/Diffusion/StochasticForceInference.py
ConfinedBrownianAnalysis/Diffusion/__init__.py
ConfinedBrownianAnalysis/Diffusion/fun_SFI.py
ConfinedBrownianAnalysis/Model/Model.py
ConfinedBrownianAnalysis/Model/__init__.py
ConfinedBrownianAnalysis/Optimize/Minimizer.py
ConfinedBrownianAnalysis/Optimize/__init__.py
ConfinedBrownianAnalysis/io/Data.py
ConfinedBrownianAnalysis/io/__init__.py
ConfinedBrownianAnalysis-1.0.3.dist-info/LICENSE
ConfinedBrownianAnalysis-1.0.3.dist-info/METADATA
ConfinedBrownianAnalysis-1.0.3.dist-info/WHEEL
ConfinedBrownianAnalysis-1.0.3.dist-info/top_level.txt
ConfinedBrownianAnalysis-1.0.3.dist-info/RECORD
