Metadata-Version: 2.1
Name: ConfinedBrownianAnalysis
Version: 1.0.3
Summary: A package to analyse 3D confined Borwnian trajectories
Author: Maxime Lavaud
Author-email: Maxime Lavaud <lavaudmaxime.ml@gmail.com>
Project-URL: Homepage, https://github.com/eXpensia/Confined_Brownian_Analysis
Project-URL: Bug Tracker, https://github.com/eXpensia/Confined_Brownian_Analysis/issues
Classifier: Programming Language :: Python :: 3
Classifier: License :: OSI Approved :: MIT License
Classifier: Operating System :: OS Independent
Requires-Python: >=3.10
License-File: LICENSE
Requires-Dist: ipympl (==0.9.2)
Requires-Dist: jupyterlab (==3.4.8)
Requires-Dist: matplotlib (==3.6.1)
Requires-Dist: numpy (==1.23.4)
Requires-Dist: scipy (==1.9.2)
Requires-Dist: seaborn (==0.11)
Requires-Dist: tqdm (==4.64.1)
Requires-Dist: dill (==0.3.5.1)
